{"0":"http:\/\/haluwarasa.indonetwork.co.id\/info","5":"http:\/\/bumi-aceh-indonesia.indonetwork.co.id\/info","6":"http:\/\/udemsstoneindonesia.indonetwork.co.id\/info","7":"http:\/\/salam-intermulo-global.indonetwork.co.id\/info","8":"http:\/\/pt_dunia_barusa.indonetwork.co.id\/info","9":"http:\/\/pt-elok-indonesia.indonetwork.co.id\/info","10":"http:\/\/wwwjictcoid.indonetwork.co.id\/info","12":"http:\/\/cv-bangun-prima.indonetwork.co.id\/info","18":"http:\/\/nurul_karya_tani.indonetwork.co.id\/info","19":"http:\/\/kontraltor-acrylic-aceh.indonetwork.co.id\/info"}