{
    "af": "Afrikaans",
    "sq": "Albanian",
    "ar": "Arabic",
    "hy": "Armenian",
    "bg": "Bulgarian",
    "my": "Burmese",
    "km": "Cambodian",
    "ca": "Catalan",
    "ch": "Chinese",
    "hr": "Croatian",
    "cs": "Czech",
    "da": "Danish",
    "nl": "Dutch",
    "en": "English",
    "et": "Estonian",
    "fa": "Farsi",
    "fj": "Fiji",
    "fi": "Finnish",
    "fr": "French",
    "ka": "Georgian",
    "de": "German",
    "el": "Greek",
    "ht": "Haitian",
    "he": "Hebrew",
    "hi": "Hindi",
    "hu": "Hungarian",
    "is": "Icelandic",
    "id": "Indonesian",
    "ga": "Irish",
    "it": "Italian",
    "jp": "Japanese",
    "jv": "Javanese",
    "ko": "Korean",
    "ku": "Kurdish",
    "la": "Latin",
    "lt": "Lithuanian",
    "ms": "Malay",
    "no": "Norwegian",
    "pl": "Polish",
    "pt": "Portuguese",
    "ro": "Romanian",
    "ru": "Russian",
    "sr": "Serbian",
    "sk": "Slovak",
    "sl": "Slovenian",
    "es": "Spanish",
    "su": "Sundanese",
    "sv": "Swedish",
    "tl": "Tagalog",
    "th": "Thai",
    "tr": "Turkish",
    "uk": "Ukrainian",
    "ur": "Urdu",
    "uz": "Uzbek",
    "vi": "Vietnamese",
    "cy": "Welsh",
    "yi": "Yiddish",
    "yo": "Yoruba",
    "zu": "Zulu"
}
